cloudCmmonUtils/__init__.py
cloudCmmonUtils/driver_options.py
cloudCmmonUtils/randomUtils.py
commonUtils/__init__.py
commonUtils/driver.py
commonUtils/driver_options.py
commonUtils/randomUtils.py
cloudCmmonUtils-0.0.8.dist-info/METADATA
cloudCmmonUtils-0.0.8.dist-info/WHEEL
cloudCmmonUtils-0.0.8.dist-info/top_level.txt
cloudCmmonUtils-0.0.8.dist-info/RECORD
