Metadata-Version: 2.1
Name: cloudCmmonUtils
Version: 0.0.8
Summary: 包含工具方法，如创建虚拟手机号，创建指定长度的随机数，等
Home-page: UNKNOWN
Author: wu weiping
Author-email: 115773673@qq.com
License: UNKNOWN
Platform: UNKNOWN
Requires-Python: >=3.6
